LICENSE.txt
MANIFEST.in
README.rst
pyproject.toml
setup.cfg
setup.py
affbio/AffRender.py
affbio/__init__.py
affbio/aff_cluster.py
affbio/cli.py
affbio/lvc.pyx
affbio/misc.py
affbio/prepare.py
affbio/structures.py
affbio/utils.py
affbio.egg-info/PKG-INFO
affbio.egg-info/SOURCES.txt
affbio.egg-info/dependency_links.txt
affbio.egg-info/entry_points.txt
affbio.egg-info/requires.txt
affbio.egg-info/top_level.txt