Metadata-Version: 1.1
Name: affbio
Version: 0.0.4.3
Summary: Affinity Propagation for structures of biomolecules. First developed for clustering of DNA origami structures (see https://doi.org/10.1093/nar/gkx1262 for details)
Home-page: http://vsb.fbb.msu.ru/rhodecode/software/aff_cluster
Author: Arthur Zalevsky
Author-email: aozalevsky@fbb.msu.ru
License: GPLv3
Keywords: clustering bioinformatics
Platform: UNKNOWN
Classifier: Development Status :: 4 - Beta
Classifier: Intended Audience :: Developers
Classifier: Topic :: Scientific/Engineering :: Bio-Informatics
Classifier: License :: OSI Approved :: GNU General Public License v3 (GPLv3)
Classifier: Programming Language :: Python :: 2
Classifier: Programming Language :: Python :: 2.7
